[
    {
        "0": {
            "specifications": {
                "0": {
                    "name": "Model",
                    "value": "Output Level Adaptation"
                },
                "1": {
                    "name": "Method",
                    "value": "non-adaptive baseline"
                },
                "2": {
                    "name": "task",
                    "value": "Synthetic Data"
                }
            },
            "Measure": "mIoU",
            "Outcome": "37.5"
        }
    },
    {
        "1": {
            "specifications": {
                "0": {
                    "name": "Model",
                    "value": "Output Level Adaptation"
                },
                "1": {
                    "name": "Method",
                    "value": "semantic segmentation output map"
                },
                "2": {
                    "name": "task",
                    "value": "Synthetic Data"
                }
            },
            "Measure": "mIoU",
            "Outcome": "45.9"
        }
    },
    {
        "2": {
            "specifications": {
                "0": {
                    "name": "Model",
                    "value": "Output Level Adaptation"
                },
                "1": {
                    "name": "Method",
                    "value": "depth output map"
                },
                "2": {
                    "name": "task",
                    "value": "Synthetic Data"
                }
            },
            "Measure": "mIoU",
            "Outcome": "43.8"
        }
    },
    {
        "3": {
            "specifications": {
                "0": {
                    "name": "Model",
                    "value": "Output Level Adaptation"
                },
                "1": {
                    "name": "Method",
                    "value": "individually aligning both semantic segmentation and depth estimation"
                },
                "2": {
                    "name": "task",
                    "value": "Synthetic Data"
                }
            },
            "Measure": "mIoU",
            "Outcome": "46.3"
        }
    },
    {
        "4": {
            "specifications": {
                "0": {
                    "name": "Model",
                    "value": "Output Level Adaptation"
                },
                "1": {
                    "name": "Method",
                    "value": "joint output space of depth estimation and semantic segmentation"
                },
                "2": {
                    "name": "task",
                    "value": "Synthetic Data"
                }
            },
            "Measure": "mIoU",
            "Outcome": "50.0"
        }
    }
]